{
  "project_info": {
    "project_number": "397312997448",
    "project_id": "spotify-20fe8",
    "storage_bucket": "spotify-20fe8.firebasestorage.app"
  },
  "client": [
    {
      "client_info": {
        "mobilesdk_app_id": "1:397312997448:android:b5bab35669fa9815a1407d",
        "android_client_info": {
          "package_name": "com.example.subscriptionmanager"
        }
      },
      "oauth_client": [],
      "api_key": [
        {
          "current_key": "AIzaSyDagoGh3szoeQ96IpLMDhN0FOmCsm3d_6U"
        }
      ],
      "services": {
        "appinvite_service": {
          "other_platform_oauth_client": []
        }
      }
    }
  ],
  "configuration_version": "1"
}
